nhtsa/__init__.py
nhtsa/client.py
nhtsa/api/__init__.py
nhtsa/api/biomechanics_test_database/__init__.py
nhtsa/api/biomechanics_test_database/index.py
nhtsa/api/biomechanics_test_database/models.py
nhtsa/api/car_seat_inspection_locator/__init__.py
nhtsa/api/car_seat_inspection_locator/index.py
nhtsa/api/car_seat_inspection_locator/models.py
nhtsa/api/complaints/__init__.py
nhtsa/api/complaints/index.py
nhtsa/api/complaints/models.py
nhtsa/api/component_test_database/__init__.py
nhtsa/api/component_test_database/index.py
nhtsa/api/component_test_database/models.py
nhtsa/api/crash_avoidance_test_database/__init__.py
nhtsa/api/crash_avoidance_test_database/index.py
nhtsa/api/crash_avoidance_test_database/models.py
nhtsa/api/investigations/__init__.py
nhtsa/api/investigations/index.py
nhtsa/api/investigations/models.py
nhtsa/api/manufacturer_communications/__init__.py
nhtsa/api/manufacturer_communications/index.py
nhtsa/api/manufacturer_communications/models.py
nhtsa/api/nhtsa_database_code_library/__init__.py
nhtsa/api/nhtsa_database_code_library/index.py
nhtsa/api/nhtsa_database_code_library/models.py
nhtsa/api/products/__init__.py
nhtsa/api/products/index.py
nhtsa/api/products/models.py
nhtsa/api/recalls/__init__.py
nhtsa/api/recalls/index.py
nhtsa/api/recalls/models.py
nhtsa/api/safety_issues/__init__.py
nhtsa/api/safety_issues/index.py
nhtsa/api/safety_issues/models.py
nhtsa/api/safetyservice/__init__.py
nhtsa/api/safetyservice/index.py
nhtsa/api/safetyservice/models.py
nhtsa/api/static_files/__init__.py
nhtsa/api/static_files/index.py
nhtsa/api/static_files/models.py
nhtsa/api/tag_lookup/__init__.py
nhtsa/api/tag_lookup/index.py
nhtsa/api/tag_lookup/models.py
nhtsa/api/tools/__init__.py
nhtsa/api/tools/index.py
nhtsa/api/vehicle_crash_test_database/__init__.py
nhtsa/api/vehicle_crash_test_database/index.py
nhtsa/api/vehicle_crash_test_database/models.py
nhtsa/api/vin_decoding/_README.py
nhtsa/api/vin_decoding/__init__.py
nhtsa/api/vin_decoding/index.py
nhtsa-0.1.7.dist-info/licenses/LICENSE
nhtsa-0.1.7.dist-info/METADATA
nhtsa-0.1.7.dist-info/WHEEL
nhtsa-0.1.7.dist-info/top_level.txt
nhtsa-0.1.7.dist-info/RECORD
