Metadata-Version: 2.4
Name: nhtsa
Version: 0.1.7
Summary: Unofficial Python SDK/wrapper for NHTSA APIs.
Home-page: https://github.com/ReedGraff/NHTSA
Author: Reed Graff
Author-email: rangergraff@gmail.com
Classifier: Programming Language :: Python :: 3
Classifier: Operating System :: OS Independent
Requires-Python: >=3.8
License-File: LICENSE
Requires-Dist: httpx
Requires-Dist: pydantic
Requires-Dist: aiofiles
Requires-Dist: python-dotenv
Requires-Dist: pillow
Requires-Dist: tqdm
Requires-Dist: beautifulsoup4
Requires-Dist: lxml
Dynamic: author
Dynamic: author-email
Dynamic: classifier
Dynamic: description
Dynamic: description-content-type
Dynamic: home-page
Dynamic: license-file
Dynamic: requires-dist
Dynamic: requires-python
Dynamic: summary
